pnio_dcp/__init__.py
pnio_dcp/dcp_constants.py
pnio_dcp/error.py
pnio_dcp/pnio_dcp.py
pnio_dcp/protocol.py
pnio_dcp/util.py
pnio_dcp/l2socket/__init__.py
pnio_dcp/l2socket/l2socket.py
pnio_dcp/l2socket/pcap_wrapper.py
pnio_dcp/l2socket/winpcap.py
pnio_dcp-1.2.0.dist-info/LICENSE.md
pnio_dcp-1.2.0.dist-info/METADATA
pnio_dcp-1.2.0.dist-info/WHEEL
pnio_dcp-1.2.0.dist-info/top_level.txt
pnio_dcp-1.2.0.dist-info/RECORD
