Metadata-Version: 2.1
Name: pnio_dcp
Version: 1.2.0
Summary: Discover and configure PROFINET devices with the PROFINET Discovery and basic Configuration Protocol (DCP) protocol.
Home-page: https://gitlab.com/pyshacks/pnio_dcp.git
Author: Dominic Schlagenhof, Alexander Riedel
Author-email: dominic.schlagenhof@codewerk.de
License: MIT © 2020-2023 Codewerk GmbH, Karlsruhe
Classifier: Development Status :: 5 - Production/Stable
Classifier: Intended Audience :: Developers
Classifier: Intended Audience :: Information Technology
Classifier: Intended Audience :: System Administrators
Classifier: Intended Audience :: Telecommunications Industry
Classifier: Topic :: Software Development :: Libraries
Classifier: Topic :: Software Development :: Libraries :: Python Modules
Classifier: Topic :: System :: Networking
Classifier: Operating System :: Microsoft :: Windows
Classifier: Operating System :: POSIX :: Linux
Classifier: License :: OSI Approved :: MIT License
Classifier: Programming Language :: Python :: 3
Classifier: Programming Language :: Python :: 3.6
Classifier: Programming Language :: Python :: 3.7
Classifier: Programming Language :: Python :: 3.8
Classifier: Programming Language :: Python :: 3.9
Classifier: Programming Language :: Python :: 3.10
Requires-Python: >=3.6
License-File: LICENSE.md
Requires-Dist: psutil
Requires-Dist: setuptools-scm
Requires-Dist: importlib-metadata
Provides-Extra: test
Requires-Dist: pytest ; extra == 'test'
